odoo/addons/attachment_delete_restrict/README.rst
odoo/addons/attachment_delete_restrict/__init__.py
odoo/addons/attachment_delete_restrict/__manifest__.py
odoo/addons/attachment_delete_restrict/i18n/attachment_delete_restrict.pot
odoo/addons/attachment_delete_restrict/i18n/ja.po
odoo/addons/attachment_delete_restrict/models/__init__.py
odoo/addons/attachment_delete_restrict/models/ir_attachment.py
odoo/addons/attachment_delete_restrict/models/ir_model.py
odoo/addons/attachment_delete_restrict/models/res_groups.py
odoo/addons/attachment_delete_restrict/models/res_users.py
odoo/addons/attachment_delete_restrict/readme/CONFIGURE.rst
odoo/addons/attachment_delete_restrict/readme/CONTRIBUTORS.rst
odoo/addons/attachment_delete_restrict/readme/DESCRIPTION.rst
odoo/addons/attachment_delete_restrict/static/description/icon.png
odoo/addons/attachment_delete_restrict/static/description/index.html
odoo/addons/attachment_delete_restrict/tests/__init__.py
odoo/addons/attachment_delete_restrict/tests/test_attachment_delete_restrict.py
odoo/addons/attachment_delete_restrict/views/ir_model_views.xml
odoo/addons/attachment_delete_restrict/views/res_groups_views.xml
odoo/addons/attachment_delete_restrict/views/res_users_views.xml
odoo12_addon_attachment_delete_restrict-12.0.1.0.0.99.dev3.dist-info/METADATA
odoo12_addon_attachment_delete_restrict-12.0.1.0.0.99.dev3.dist-info/WHEEL
odoo12_addon_attachment_delete_restrict-12.0.1.0.0.99.dev3.dist-info/top_level.txt
odoo12_addon_attachment_delete_restrict-12.0.1.0.0.99.dev3.dist-info/RECORD
